.gitignore
LICENSE
README.markdown
bottle.py
cony.py
setup.py
cony.egg-info/PKG-INFO
cony.egg-info/SOURCES.txt
cony.egg-info/dependency_links.txt
cony.egg-info/requires.txt
cony.egg-info/top_level.txt
examples/__init__.py
examples/lang.py
examples/search.py