Metadata-Version: 1.0
Name: cony
Version: 0.2.0
Summary: "Cony" is a tool to write smart bookmarks in python and to share them across all your browsers and with a group of people or the whole world. This project inspired by Facebook's bunny1.
Home-page: http://dev.svetlyak.ru/cony/
Author: Alexander Artemenko
Author-email: svetlyak.40wt@gmail.com
License: New BSD License
Keywords: bottle webapp smart bookmark browser
Platform: UNKNOWN
Classifier: Development Status :: 4 - Beta
Classifier: Environment :: Web Environment
Classifier: Intended Audience :: Developers
Classifier: Intended Audience :: System Administrators
Classifier: Intended Audience :: End Users/Desktop
Classifier: License :: OSI Approved :: BSD License
Classifier: Programming Language :: Python
Classifier: Topic :: Internet :: WWW/HTTP :: WSGI :: Server
